asyncapi_docgen/__init__.py
asyncapi_docgen/asgi.py
asyncapi_docgen/constants.py
asyncapi_docgen/docs.py
asyncapi_docgen/models.py
asyncapi_docgen/utils.py
asyncapi_docgen-0.0.1.dist-info/LICENSE
asyncapi_docgen-0.0.1.dist-info/METADATA
asyncapi_docgen-0.0.1.dist-info/WHEEL
asyncapi_docgen-0.0.1.dist-info/top_level.txt
asyncapi_docgen-0.0.1.dist-info/RECORD
