Metadata-Version: 2.1
Name: asyncapi-docgen
Version: 0.0.1
Summary: AsyncAPI Documentation Generator
Home-page: https://github.com/Voltane-EU/asyncapi-docgen
Author: Manuel Stingl
Author-email: opensource@voltane.eu
License: GNU LGPLv2.1
Classifier: Programming Language :: Python :: 3
Classifier: License :: OSI Approved :: GNU Lesser General Public License v2 or later (LGPLv2+)
Classifier: Operating System :: OS Independent
Classifier: Topic :: Utilities
Requires-Python: >=3.6
License-File: LICENSE
Requires-Dist: pydantic (>=1.9.0)
